privugger/__init__.py
privugger/attacker/__init__.py
privugger/attacker/distributions.py
privugger/attacker/generators.py
privugger/attacker/metrics.py
privugger/data_structures/__init__.py
privugger/data_structures/dataset.py
privugger/data_structures/program.py
privugger/distributions/__init__.py
privugger/distributions/continuous.py
privugger/distributions/discrete.py
privugger/inference/__init__.py
privugger/inference/inference.py
privugger/inference/typed.py
privugger/measures/__init__.py
privugger/measures/kl_divergence.py
privugger/measures/mutual_information.py
privugger/transformer/__init__.py
privugger/transformer/annotation_types.py
privugger/transformer/continuous.py
privugger/transformer/datastructures.py
privugger/transformer/discrete.py
privugger/transformer/method.py
privugger/transformer/program_output.py
privugger/transformer/theano_types.py
privugger/transformer/type_decoration.py
privugger/transformer/PyMC3/__init__.py
privugger/transformer/PyMC3/annotation_types.py
privugger/transformer/PyMC3/program_output.py
privugger/transformer/PyMC3/theano_types.py
privugger/transformer/PyMC3/type_decoration.py
privugger-0.0.10.dist-info/LICENSE
privugger-0.0.10.dist-info/METADATA
privugger-0.0.10.dist-info/WHEEL
privugger-0.0.10.dist-info/top_level.txt
privugger-0.0.10.dist-info/RECORD
