Metadata-Version: 2.1
Name: privugger
Version: 0.0.10
Summary: Privacy risk analysis library for Python programs.
Home-page: https://github.com/itu-square/privugger
Author: Raúl Pardo, Mathias Valdbjørn Jørgensen, Peter Daly, and Rasmus Carl Rønneberg
Author-email: raup@itu.dk
License: Apache license
Platform: UNKNOWN
